odoo/addons/delivery_seur/README.rst
odoo/addons/delivery_seur/__init__.py
odoo/addons/delivery_seur/__manifest__.py
odoo/addons/delivery_seur/doc/SEUR_Track_and_Tracing_Webservice.doc
odoo/addons/delivery_seur/doc/Servicios_WEB_Seur.doc
odoo/addons/delivery_seur/doc/WS_Cancelation_and_Modification_shipments_webservice.doc
odoo/addons/delivery_seur/doc/WebServices_Integration_Process_ENG_PDF.docx
odoo/addons/delivery_seur/doc/WebServices_Integration_Process_ENG_ZEBRA.docx
odoo/addons/delivery_seur/i18n/ca.po
odoo/addons/delivery_seur/i18n/delivery_seur.pot
odoo/addons/delivery_seur/i18n/es.po
odoo/addons/delivery_seur/models/__init__.py
odoo/addons/delivery_seur/models/delivery_carrier.py
odoo/addons/delivery_seur/models/seur_request.py
odoo/addons/delivery_seur/readme/CONTRIBUTORS.rst
odoo/addons/delivery_seur/readme/DESCRIPTION.rst
odoo/addons/delivery_seur/readme/USAGE.rst
odoo/addons/delivery_seur/static/description/icon.png
odoo/addons/delivery_seur/static/description/index.html
odoo/addons/delivery_seur/tests/__init__.py
odoo/addons/delivery_seur/tests/test_delivery_seur.py
odoo/addons/delivery_seur/views/delivery_carrier_views.xml
odoo14_addon_delivery_seur-14.0.1.0.1.dev5.dist-info/METADATA
odoo14_addon_delivery_seur-14.0.1.0.1.dev5.dist-info/WHEEL
odoo14_addon_delivery_seur-14.0.1.0.1.dev5.dist-info/top_level.txt
odoo14_addon_delivery_seur-14.0.1.0.1.dev5.dist-info/RECORD
